odoo/addons/mrp_production_move_line_auto_fill/README.rst
odoo/addons/mrp_production_move_line_auto_fill/__init__.py
odoo/addons/mrp_production_move_line_auto_fill/__manifest__.py
odoo/addons/mrp_production_move_line_auto_fill/i18n/it.po
odoo/addons/mrp_production_move_line_auto_fill/i18n/mrp_production_move_line_auto_fill.pot
odoo/addons/mrp_production_move_line_auto_fill/models/__init__.py
odoo/addons/mrp_production_move_line_auto_fill/models/mrp_production.py
odoo/addons/mrp_production_move_line_auto_fill/models/stock_move.py
odoo/addons/mrp_production_move_line_auto_fill/readme/CONTRIBUTORS.rst
odoo/addons/mrp_production_move_line_auto_fill/readme/DESCRIPTION.rst
odoo/addons/mrp_production_move_line_auto_fill/static/description/icon.png
odoo/addons/mrp_production_move_line_auto_fill/static/description/index.html
odoo/addons/mrp_production_move_line_auto_fill/tests/__init__.py
odoo/addons/mrp_production_move_line_auto_fill/tests/test_mrp_production_move_line_auto_fill.py
odoo/addons/mrp_production_move_line_auto_fill/views/mrp_production_views.xml
odoo_addon_mrp_production_move_line_auto_fill-16.0.1.0.0.4.dist-info/METADATA
odoo_addon_mrp_production_move_line_auto_fill-16.0.1.0.0.4.dist-info/WHEEL
odoo_addon_mrp_production_move_line_auto_fill-16.0.1.0.0.4.dist-info/top_level.txt
odoo_addon_mrp_production_move_line_auto_fill-16.0.1.0.0.4.dist-info/RECORD
