Metadata-Version: 2.1
Name: odoo-addon-mrp_production_move_line_auto_fill
Version: 16.0.1.0.0.4
Summary: Mrp Production Move Line Auto Fill
Home-page: https://github.com/OCA/manufacture
Author: Quartile, Odoo Community Association (OCA)
Author-email: support@odoo-community.org
License: AGPL-3
Classifier: Programming Language :: Python
Classifier: Framework :: Odoo
Classifier: Framework :: Odoo :: 16.0
Classifier: License :: OSI Approved :: GNU Affero General Public License v3
Requires-Python: >=3.10
Requires-Dist: odoo-addon-stock-move-line-auto-fill<16.1dev,>=16.0dev
Requires-Dist: odoo<16.1dev,>=16.0a
